AUTHORS.rst
CONTRIBUTING.rst
HISTORY.rst
MANIFEST.in
README.rst
setup.cfg
setup.py
docs/Makefile
docs/api.rst
docs/authors.rst
docs/conf.py
docs/contributing.rst
docs/history.rst
docs/index.rst
docs/installation.rst
docs/make.bat
docs/testenvironment.rst
streamsets/testenvironments/__init__.py
streamsets/testenvironments/cli.py
streamsets/testenvironments/environments.yaml
streamsets/testenvironments/exceptions.py
streamsets/testenvironments/models.py
streamsets/testenvironments/utils.py
streamsets/testenvironments/actions/__init__.py
streamsets/testenvironments/actions/start.py
streamsets/testenvironments/actions/stop.py
streamsets_testenvironments.egg-info/PKG-INFO
streamsets_testenvironments.egg-info/SOURCES.txt
streamsets_testenvironments.egg-info/dependency_links.txt
streamsets_testenvironments.egg-info/entry_points.txt
streamsets_testenvironments.egg-info/not-zip-safe
streamsets_testenvironments.egg-info/requires.txt
streamsets_testenvironments.egg-info/top_level.txt
tests/__init__.py
tests/test_ste.py