Metadata-Version: 1.1
Name: streamsets-testenvironments
Version: 0.0.2
Summary: Spin environments for StreamSets products
Home-page: https://github.com/streamsets/testenvironments
Author: StreamSets, Inc.
Author-email: eng-productivity@streamsets.com
License: OSI Approved :: Apache Software License
Keywords: ste
Platform: UNKNOWN
Classifier: Development Status :: 4 - Beta
Classifier: Intended Audience :: Developers
Classifier: License :: Other/Proprietary License
Classifier: Natural Language :: English
Classifier: Programming Language :: Python :: 3
Classifier: Programming Language :: Python :: 3.3
Classifier: Programming Language :: Python :: 3.4
Classifier: Programming Language :: Python :: 3.5
Classifier: Programming Language :: Python :: 3.6
